flintpy/__init__.py
flintpy/flintpy.py
flintpy/kernels.py
flintpy/plotting.py
flintpy/py.typed
flintpy/utils.py
flintpy_nmr-0.1.2.dist-info/LICENSE.rst
flintpy_nmr-0.1.2.dist-info/METADATA
flintpy_nmr-0.1.2.dist-info/WHEEL
flintpy_nmr-0.1.2.dist-info/RECORD
