Metadata-Version: 2.3
Name: flintpy-nmr
Version: 0.1.2
Summary: Python implementation of FLINT algorithm for NMR relaxation data.
Keywords: flintpy,flintpy-nmr,nmr
Author: Raquel Serial
Author-email: raquelserial@gmail.com>
Requires-Python: <3.13,>=3.10
Classifier: Development Status :: 2 - Pre-Alpha
Classifier: Intended Audience :: Developers
Classifier: License :: OSI Approved :: GNU General Public License v3 (GPLv3)
Classifier: Natural Language :: English
Classifier: Programming Language :: Python :: 3
Classifier: Programming Language :: Python :: 3.10
Classifier: Programming Language :: Python :: 3.11
Classifier: Programming Language :: Python :: 3.12
Requires-Dist: numpy (>=2.0.1,<3.0.0)
Requires-Dist: plotly (>=5.23.0,<6.0.0)
Project-URL: Bug Tracker, https://github.com/rserial/flintpy/issues
Project-URL: Documentation, https://flintpy.readthedocs.io
Project-URL: Homepage, https://github.com/rserial/flintpy
Project-URL: Repository, https://github.com/rserial/flintpy
